Prochestra-1.1.2.dist-info/DESCRIPTION.rst
Prochestra-1.1.2.dist-info/METADATA
Prochestra-1.1.2.dist-info/RECORD
Prochestra-1.1.2.dist-info/WHEEL
Prochestra-1.1.2.dist-info/entry_points.txt
Prochestra-1.1.2.dist-info/metadata.json
Prochestra-1.1.2.dist-info/top_level.txt
prochestra/__init__.py
prochestra/__main__.py
