Metadata-Version: 2.0
Name: Prochestra
Version: 1.1.2
Summary: Run multiple processes with dependencies with one call.
Home-page: https://github.com/mastersign/prochestra
Author: Tobias Kiertscher
Author-email: dev@mastersign.de
License: UNKNOWN
Platform: UNKNOWN
Requires-Dist: pyyaml (>=3.0.0)
